moneyball
tests
