Metadata-Version: 2.1
Name: moneyball
Version: 0.0.225
Summary: A library for determining what bets to make.
Home-page: https://github.com/8W9aG/moneyball
Author: Will Sackfield
Author-email: will.sackfield@gmail.com
License: MIT
Keywords: sports betting
Classifier: License :: OSI Approved :: MIT License
Classifier: Programming Language :: Python :: 3
License-File: LICENSE
Requires-Dist: pandas>=2.2.3
Requires-Dist: numpy>=1.26.4
Requires-Dist: optuna>=4.2.0
Requires-Dist: pytz>=2024.2
Requires-Dist: python-dateutil>=2.9.0.post0
Requires-Dist: sportsball>=0.34.0
Requires-Dist: tqdm>=4.67.1
Requires-Dist: joblib>=1.4.2
Requires-Dist: matplotlib>=3.10.0
Requires-Dist: pyfolio-reloaded>=0.9.8
Requires-Dist: fullmonte>=0.0.4
Requires-Dist: wavetrainer>=0.2.34
Requires-Dist: riskfolio-lib>=7.0.0
Requires-Dist: sportsfeatures>=0.0.106
Requires-Dist: empyrical-reloaded>=0.5.11
Requires-Dist: textfeats>=0.1.4
